{
  "MORDREDSABER-STRIKE.title": "打击",
  "MORDREDSABER-STRIKE.description": "#造成!D!点伤害。",
  "MORDREDSABER-DEFEND.title": "防御",
  "MORDREDSABER-DEFEND.description": "#获得!B!点格挡。",
  "MORDREDSABER-REBELLION.title": "叛逆",
  "MORDREDSABER-REBELLION.description": "#造成!D!点伤害，随后摘下头盔：进入*叛逆形态。",
  "MORDREDSABER-LOWER_THE_VISOR.title": "落下面甲",
  "MORDREDSABER-LOWER_THE_VISOR.description": "#戴上头盔：进入*假面骑士形态。获得!B!点格挡与!NpCharge!点*NP值。",

  "MORDREDSABER-SLASH_OF_CLARENT.title": "克拉伦特斩",
  "MORDREDSABER-SLASH_OF_CLARENT.description": "#造成!D!点伤害。获得!Stars!颗*暴击星*。",
  "MORDREDSABER-REBELS_DOUBLE_EDGE.title": "叛逆双刃",
  "MORDREDSABER-REBELS_DOUBLE_EDGE.description": "#造成!D!点伤害2次。获得!NpCharge!点*NP值。",
  "MORDREDSABER-ONSLAUGHT_OF_HATRED.title": "憎恶猛击",
  "MORDREDSABER-ONSLAUGHT_OF_HATRED.description": "#造成!D!点伤害。对精英与首领：额外造成!Authority!点。",
  "MORDREDSABER-SPARKS_OF_THE_HELM.title": "头盔火花",
  "MORDREDSABER-SPARKS_OF_THE_HELM.description": "#获得!B!点格挡。若你处于*假面骑士形态：获得!NpCharge!点*NP值。",
  "MORDREDSABER-LOUDMOUTHS_TAUNT.title": "大嘴挑衅",
  "MORDREDSABER-LOUDMOUTHS_TAUNT.description": "#施加!Weak!层虚弱。获得!Stars!颗*暴击星*。",
  "MORDREDSABER-SPOILS_OF_CAMELOT.title": "卡美洛战利品",
  "MORDREDSABER-SPOILS_OF_CAMELOT.description": "#若你拥有至少!NpCost!点*NP值：消耗之，获得!Stars!颗*暴击星*。",
  "MORDREDSABER-TRIBUTE_TO_THE_THRONE.title": "王座供奉",
  "MORDREDSABER-TRIBUTE_TO_THE_THRONE.description": "#若你拥有至少!StarCost!颗*暴击星*：消耗之，获得!NpCharge!点*NP值。",
  "MORDREDSABER-MANA_IGNITION.title": "魔力点火",
  "MORDREDSABER-MANA_IGNITION.description": "#获得!NpCharge!点*NP值。",
  "MORDREDSABER-BATTLE_INSTINCT.title": "战斗直觉",
  "MORDREDSABER-BATTLE_INSTINCT.description": "#若你拥有至少!StarCost!颗*暴击星*：消耗之，抽!C!张牌。",
  "MORDREDSABER-RESIDUAL_LIGHTNING.title": "残雷",
  "MORDREDSABER-RESIDUAL_LIGHTNING.description": "#对所有敌人造成!D!点伤害。获得!Stars!颗*暴击星*。",
  "MORDREDSABER-INSOLENT_STRIKE.title": "无礼一击",
  "MORDREDSABER-INSOLENT_STRIKE.description": "#造成!D!点伤害。若你本回合消耗过暴击：获得!NpCharge!点*NP值。",
  "MORDREDSABER-WAR_CRY.title": "战吼",
  "MORDREDSABER-WAR_CRY.description": "#获得!NpCharge!点*NP值与!Stars!颗*暴击星*。",
  "MORDREDSABER-INSOLENT_GUARD.title": "无礼防御",
  "MORDREDSABER-INSOLENT_GUARD.description": "#获得!B!点格挡与!NpCharge!点*NP值。",
  "MORDREDSABER-TOURNAMENT_FOOTWORK.title": "比武步法",
  "MORDREDSABER-TOURNAMENT_FOOTWORK.description": "#获得!B!点格挡与!NpCharge!点*NP值。",
  "MORDREDSABER-PROUD_GREATSWORD.title": "傲慢大剑",
  "MORDREDSABER-PROUD_GREATSWORD.description": "#造成!D!点伤害。失去!HpLoss!点生命。",
  "MORDREDSABER-DEFIANCE_OF_AUTHORITY.title": "蔑视权威",
  "MORDREDSABER-DEFIANCE_OF_AUTHORITY.description": "#造成!D!点伤害。对精英与首领：获得!NpCharge!点*NP值。",
  "MORDREDSABER-LIGHTNING_SPLINTERS.title": "雷霆碎片",
  "MORDREDSABER-LIGHTNING_SPLINTERS.description": "#对随机敌人造成!D!点伤害3次。获得!Stars!颗*暴击星*。",
  "MORDREDSABER-RIDE_THE_STOLEN.title": "骑乘掠夺",
  "MORDREDSABER-RIDE_THE_STOLEN.description": "#抽!C!张牌。获得!Stars!颗*暴击星*。",
  "MORDREDSABER-KNIGHTS_STEADFASTNESS.title": "骑士坚毅",
  "MORDREDSABER-KNIGHTS_STEADFASTNESS.description": "#获得!B!点格挡。若你处于*假面骑士形态：获得!NpCharge!点*NP值。",
  "MORDREDSABER-DONT_CALL_ME_A_GIRL.title": "别叫我小姑娘！",
  "MORDREDSABER-DONT_CALL_ME_A_GIRL.description": "#消耗。获得!Stars!颗*暴击星*与!NpCharge!点*NP值。",

  "MORDREDSABER-MANA_BURST_A.title": "魔力放出A",
  "MORDREDSABER-MANA_BURST_A.description": "#消耗。本回合，你的攻击牌额外造成!Strength!点伤害。",
  "MORDREDSABER-KNIGHT_OF_RED_LIGHTNING_A_PLUS.title": "赤雷骑士A+",
  "MORDREDSABER-KNIGHT_OF_RED_LIGHTNING_A_PLUS.description": "#你的攻击牌额外造成!Attack!点伤害。你的暴击额外造成!CritBonus!点伤害。",
  "MORDREDSABER-INSTINCT_B.title": "直感B",
  "MORDREDSABER-INSTINCT_B.description": "#消耗。获得!Stars!颗*暴击星*并抽!C!张牌。",
  "MORDREDSABER-CIGARETTE_LION_B_PLUS.title": "香烟雄狮B+",
  "MORDREDSABER-CIGARETTE_LION_B_PLUS.description": "#打出时，获得!Stars!颗*暴击星*。每当你获得一个暴击时，抽1张牌。",
  "MORDREDSABER-SECRET_OF_PEDIGREE_E_X.title": "不贞隐藏之兜EX",
  "MORDREDSABER-SECRET_OF_PEDIGREE_E_X.description": "#消耗。移除你自身所有的减益效果。获得!B!点格挡与!NpCharge!点*NP值。若你处于*假面骑士形态：额外获得!MaskedNp!点*NP值。",
  "MORDREDSABER-LIGHTNING_OF_CLARENT.title": "克拉伦特之雷",
  "MORDREDSABER-LIGHTNING_OF_CLARENT.description": "#造成!D!点伤害。获得!Stars!颗*暴击星*。",
  "MORDREDSABER-STORM_OF_STEEL.title": "钢铁风暴",
  "MORDREDSABER-STORM_OF_STEEL.description": "#造成!D!点伤害3次。获得!Stars!颗*暴击星*。",
  "MORDREDSABER-DEFIANT_CUT.title": "挑衅斩",
  "MORDREDSABER-DEFIANT_CUT.description": "#造成!D!点伤害。对精英与首领：获得!Stars!颗*暴击星*。",
  "MORDREDSABER-RECKLESS_CHARGE.title": "鲁莽冲锋",
  "MORDREDSABER-RECKLESS_CHARGE.description": "#造成!D!点伤害。",
  "MORDREDSABER-LIGHTNING_SPEED.title": "雷速",
  "MORDREDSABER-LIGHTNING_SPEED.description": "#造成!D!点伤害。处于*叛逆形态时：获得!Stars!颗*暴击星*。",
  "MORDREDSABER-DENTED_HELM.title": "凹陷头盔",
  "MORDREDSABER-DENTED_HELM.description": "#获得!B!点格挡。处于*假面骑士形态时：获得!Stars!颗*暴击星*。",
  "MORDREDSABER-ROAR_OF_REBELLION.title": "叛逆咆哮",
  "MORDREDSABER-ROAR_OF_REBELLION.description": "#切换至你的相反形态。抽!C!张牌。",
  "MORDREDSABER-LIGHTNING_VISIT.title": "闪电造访",
  "MORDREDSABER-LIGHTNING_VISIT.description": "#切换形态。在你的回合结束时，切回原形态。+切回时，获得!Stars!颗*暴击星*。+",
  "MORDREDSABER-RUDE_KICK.title": "无礼飞踢",
  "MORDREDSABER-RUDE_KICK.description": "#造成!D!点伤害。施加!Vulnerable!层易伤。若你已就绪一个暴击：改为施加2层易伤。",
  "MORDREDSABER-PLUNDER_OF_THE_ROYAL_HOARD.title": "王室宝库劫掠",
  "MORDREDSABER-PLUNDER_OF_THE_ROYAL_HOARD.description": "#消耗。获得!NpCharge!点*NP值与!Stars!颗*暴击星*。",
  "MORDREDSABER-CHAINED_LIGHTNING.title": "连锁闪电",
  "MORDREDSABER-CHAINED_LIGHTNING.description": "#对所有敌人造成!D!点伤害。若你本回合消耗过暴击：对所有敌人额外造成!Bonus!点。",
  "MORDREDSABER-DRAGONS_BLOOD.title": "龙之血",
  "MORDREDSABER-DRAGONS_BLOOD.description": "#在你的回合开始时，获得!NpCharge!点*NP值与!B!点格挡。",
  "MORDREDSABER-ACCUMULATED_HATRED.title": "积怨",
  "MORDREDSABER-ACCUMULATED_HATRED.description": "#每当你失去生命时，获得10点*NP值（每回合至多!MaxProcs!次）。",
  "MORDREDSABER-BANNER_OF_REBELLION.title": "叛逆旗帜",
  "MORDREDSABER-BANNER_OF_REBELLION.description": "#每次你切换形态时，获得!Stars!颗*暴击星*与!NpCharge!点*NP值+并抽!C!张牌+。",
  "MORDREDSABER-DEMANDED_DUEL.title": "强求决斗",
  "MORDREDSABER-DEMANDED_DUEL.description": "#对一名敌人施加!Weak!层虚弱与!Vulnerable!层易伤。获得!NpCharge!点*NP值。",
  "MORDREDSABER-FATHERS_SWORD.title": "父亲之剑",
  "MORDREDSABER-FATHERS_SWORD.description": "#造成!D!点伤害。若你拥有至少!Threshold!点*NP值（不消耗）：额外造成!Bonus!点。",
  "MORDREDSABER-ROYAL_TANTRUM.title": "王室任性",
  "MORDREDSABER-ROYAL_TANTRUM.description": "#造成!D!点伤害。失去!HpLoss!点生命。",
  "MORDREDSABER-TOURNAMENT_GUARD.title": "比武防御",
  "MORDREDSABER-TOURNAMENT_GUARD.description": "#获得!B!点格挡与!Stars!颗*暴击星*。",
  "MORDREDSABER-ILL_REPAID_LOYALTY.title": "错付的忠诚",
  "MORDREDSABER-ILL_REPAID_LOYALTY.description": "#消耗。回复!H!点生命。获得!NpCharge!点*NP值。",
  "MORDREDSABER-HOMUNCULUS_ACCELERATION.title": "人造人加速",
  "MORDREDSABER-HOMUNCULUS_ACCELERATION.description": "#每回合你第一次消耗暴击时，获得!Stars!颗*暴击星*。",
  "MORDREDSABER-DOUBLE_REBELLION.title": "双重叛逆",
  "MORDREDSABER-DOUBLE_REBELLION.description": "#造成!D!点伤害。若你本场战斗已切换过形态：获得!Stars!颗*暴击星*与!NpCharge!点*NP值。",
  "MORDREDSABER-SCORN_FOR_THE_THRONE.title": "蔑视王座",
  "MORDREDSABER-SCORN_FOR_THE_THRONE.description": "#获得!NpCharge!点*NP值。对精英与首领：额外获得!Authority!点。",
  "MORDREDSABER-TREAT_ME_AS_A_KNIGHT.title": "把我当骑士对待",
  "MORDREDSABER-TREAT_ME_AS_A_KNIGHT.description": "#抽!C!张牌。若你处于*假面骑士形态：额外抽!MaskedDraw!张。",

  "MORDREDSABER-CLARENT_BLOOD_ARTHUR_MANUAL.title": "克拉伦特·血染亚瑟",
  "MORDREDSABER-CLARENT_BLOOD_ARTHUR_MANUAL.description": "#若你处于*假面状态，先摘下头盔。消耗你全部的*NP值，至少!ChargeCost!点。对所有敌人造成!D!点伤害!Hits!次；对精英与首领，每击额外!Authority!点；每超过最低值20点NP值，每击再追加1点。随后获得!Refund!点*NP值。",
  "MORDREDSABER-MANA_BURST_RED_LIGHTNING.title": "魔力放出·赤雷",
  "MORDREDSABER-MANA_BURST_RED_LIGHTNING.description": "#消耗你全部的*NP值，至少!ChargeCost!点。造成!D!点伤害，每超过最低值10点NP值再追加!OverchargeDamage!点。",
  "MORDREDSABER-BEHEADING_OF_THE_USURPER.title": "篡位者斩首",
  "MORDREDSABER-BEHEADING_OF_THE_USURPER.description": "#造成!D!点伤害。对精英与首领：额外造成!Authority!点。",
  "MORDREDSABER-HUNDRED_SHATTERED_SWORDS.title": "百剑碎裂",
  "MORDREDSABER-HUNDRED_SHATTERED_SWORDS.description": "#仅在拥有!StarCost!颗或更多*暴击星*时可打出：消耗之。造成!D!点伤害。",
  "MORDREDSABER-AVALANCHE_OF_HATRED.title": "憎恶雪崩",
  "MORDREDSABER-AVALANCHE_OF_HATRED.description": "#造成!D!点伤害4次。若你本回合消耗过暴击：每击额外!CritBonus!点。",
  "MORDREDSABER-CAMLANN.title": "卡姆兰",
  "MORDREDSABER-CAMLANN.description": "#消耗。获得1层硬撑。触发时，获得100点*NP值+与50颗*暴击星*+。",
  "MORDREDSABER-CRIMSON_LIGHTNING_CLIMAX_POWER.title": "绯红闪电",
  "MORDREDSABER-CRIMSON_LIGHTNING_CLIMAX_POWER.description": "#消耗。永久进入*绯红闪电形态：你的攻击牌额外造成2点伤害，每回合获得5点*NP值，保留至多10点格挡，无任何惩罚。",
  "MORDREDSABER-SECRET_REVEALED.title": "秘密揭露",
  "MORDREDSABER-SECRET_REVEALED.description": "#每当你摘下头盔（进入*叛逆形态）时：获得!Stars!颗*暴击星*并抽!C!张牌。",
  "MORDREDSABER-CROWN_OF_LIGHTNING.title": "雷之冠",
  "MORDREDSABER-CROWN_OF_LIGHTNING.description": "#在你的回合开始时，获得!Stars!颗*暴击星*。",
  "MORDREDSABER-AMBITION_FOR_THE_THRONE.title": "王座野望",
  "MORDREDSABER-AMBITION_FOR_THE_THRONE.description": "#在你的回合开始时，获得!NpCharge!点*NP值。",
  "MORDREDSABER-THE_MOST_RADIANT_SWORD.title": "最耀眼之剑",
  "MORDREDSABER-THE_MOST_RADIANT_SWORD.description": "#你的暴击额外造成!CritBonus!点伤害，且每当你消耗暴击时，额外获得!NpCharge!点*NP值。",
  "MORDREDSABER-KAIRIS_COMMAND_SEAL.title": "凯利的令咒",
  "MORDREDSABER-KAIRIS_COMMAND_SEAL.description": "#消耗。获得!NpCharge!点*NP值。",
  "MORDREDSABER-CLAIM_CALIBURN.title": "夺取石中剑",
  "MORDREDSABER-CLAIM_CALIBURN.description": "#消耗。将!C!张来自你卡池的随机稀有牌加入手牌，本回合费用为0。",
  "MORDREDSABER-FEAST_AFTER_BATTLE.title": "战后宴席",
  "MORDREDSABER-FEAST_AFTER_BATTLE.description": "#消耗。回复!H!点生命。获得!NpCharge!点*NP值。",
  "MORDREDSABER-STORM_OF_CAMELOT.title": "卡美洛风暴",
  "MORDREDSABER-STORM_OF_CAMELOT.description": "#对所有敌人造成!D!点伤害。获得!Stars!颗*暴击星*。",
  "MORDREDSABER-COUP_D_ETAT.title": "政变",
  "MORDREDSABER-COUP_D_ETAT.description": "#消耗。造成!D!点伤害。",
  "MORDREDSABER-SABERFACE.title": "同脸",
  "MORDREDSABER-SABERFACE.description": "#每回合敌人第一次命中你时：获得!Stars!颗*暴击星*+与!NpCharge!点*NP值+。",
  "MORDREDSABER-DENIED_INHERITANCE.title": "被否定的继承",
  "MORDREDSABER-DENIED_INHERITANCE.description": "#消耗。获得!NpCharge!点*NP值与!Stars!颗*暴击星*。",
  "MORDREDSABER-DOUBLE_EDGE_OF_HATRED.title": "憎恶双刃",
  "MORDREDSABER-DOUBLE_EDGE_OF_HATRED.description": "#处于*叛逆形态时，你的攻击牌额外造成!AttackBonus!点伤害。",
  "MORDREDSABER-MEMORY_OF_TRIFAS.title": "特里法斯的记忆",
  "MORDREDSABER-MEMORY_OF_TRIFAS.description": "#在你的回合开始时，回复!Heal!点生命并获得!NpCharge!点*NP值。",

  "MORDREDSABER-CLARENT_BLOOD_ARTHUR_UNLEASHED.title": "克拉伦特·血染亚瑟：解放",
  "MORDREDSABER-CLARENT_BLOOD_ARTHUR_UNLEASHED.description": "#保留。消耗。若你处于*假面状态，先摘下头盔。消耗你全部的*NP值，至少100点。对所有敌人造成!D!点伤害!Hits!次；对精英与首领，每击额外!Authority!点；每超过100的20点NP值，每击再追加1点。随后获得!Refund!点*NP值。",
  "MORDREDSABER-CLARENT_BLOOD_ARTHUR_INTERLUDE.title": "克拉伦特·血染亚瑟：幕间",
  "MORDREDSABER-CLARENT_BLOOD_ARTHUR_INTERLUDE.description": "#保留。消耗。消耗你全部的*NP值，至少100点。对所有敌人造成!D!点伤害!Hits!次；对精英与首领，每击额外!Authority!点；每超过100的15点NP值，每击再追加1点。随后获得!Refund!点*NP值。"
}
